acido/__init__.py
acido/cli.py
acido/azure_utils/BlobManager.py
acido/azure_utils/InstanceManager.py
acido/azure_utils/ManagedIdentity.py
acido/azure_utils/NetworkManager.py
acido/azure_utils/VaultManager.py
acido/azure_utils/__init__.py
acido/utils/__init__.py
acido/utils/crypto_utils.py
acido/utils/decoration.py
acido/utils/functions.py
acido/utils/lambda_safe_pool.py
acido/utils/lambda_utils.py
acido/utils/shell_utils.py
acido/utils/turnstile_utils.py
acido-0.40.2.dist-info/licenses/LICENSE
acido-0.40.2.dist-info/licenses/LICENSE-MIT
acido-0.40.2.dist-info/METADATA
acido-0.40.2.dist-info/WHEEL
acido-0.40.2.dist-info/entry_points.txt
acido-0.40.2.dist-info/top_level.txt
acido-0.40.2.dist-info/RECORD
