Metadata-Version: 2.4
Name: acido
Version: 0.40.2
Summary: Azure Container Instance Distributed Operations
Home-page: https://github.com/merabytes/acido
Author: Xavier Álvarez
Author-email: xalvarez@merabytes.com
License: MIT
Keywords: Security,Cloud Computing,Red Team,Pentesting
Classifier: Intended Audience :: Developers
Classifier: Natural Language :: English
Classifier: License :: OSI Approved :: MIT License
Classifier: Programming Language :: Python :: 3
Classifier: Programming Language :: Python :: 3.7
Classifier: Programming Language :: Python :: 3.8
Classifier: Programming Language :: Python :: 3.9
License-File: LICENSE
License-File: LICENSE-MIT
Requires-Dist: azure-cli
Requires-Dist: azure-core
Requires-Dist: azure-mgmt-core
Requires-Dist: azure.identity
Requires-Dist: azure.keyvault.secrets
Requires-Dist: azure.storage.blob
Requires-Dist: azure.mgmt.network
Requires-Dist: websockets
Requires-Dist: huepy
Requires-Dist: msrestazure
Requires-Dist: beaupy==3.8.2
Requires-Dist: tqdm
Requires-Dist: cryptography
Dynamic: author
Dynamic: author-email
Dynamic: classifier
Dynamic: description
Dynamic: description-content-type
Dynamic: home-page
Dynamic: keywords
Dynamic: license
Dynamic: license-file
Dynamic: requires-dist
Dynamic: summary
